mtest/__init__.py
mtest/ks.py
mtest/mtest.py
mtest/utils.py
mtest_py-0.1.4.dist-info/METADATA
mtest_py-0.1.4.dist-info/WHEEL
mtest_py-0.1.4.dist-info/top_level.txt
mtest_py-0.1.4.dist-info/RECORD
