Metadata-Version: 2.4
Name: mtest_py
Version: 0.1.4
Summary: A Procedure for Multicollinearity Testing using Bootstrap
Author: Víctor Morales-Oñate
License-Expression: MIT
Project-URL: Homepage, https://github.com/vmoprojs/mtest-py
Project-URL: Issues, https://github.com/vmoprojs/mtest-py/issues
Keywords: multicollinearity,bootstrap,VIF,Klein,regression,statistics
Classifier: Development Status :: 4 - Beta
Classifier: Intended Audience :: Science/Research
Classifier: Programming Language :: Python :: 3
Classifier: Programming Language :: Python :: 3 :: Only
Classifier: Programming Language :: Python :: 3.9
Classifier: Programming Language :: Python :: 3.10
Classifier: Programming Language :: Python :: 3.11
Classifier: Programming Language :: Python :: 3.12
Classifier: Topic :: Scientific/Engineering
Classifier: Topic :: Scientific/Engineering :: Mathematics
Classifier: Topic :: Scientific/Engineering :: Information Analysis
Requires-Python: >=3.9
Requires-Dist: numpy>=1.24
Requires-Dist: pandas>=2.0
Requires-Dist: scipy>=1.10
Provides-Extra: dev
Requires-Dist: pytest>=8.0; extra == "dev"
Requires-Dist: statsmodels>=0.14; extra == "dev"
